Metadata-Version: 1.1
Name: pyaffy
Version: 0.2.0
Summary: pyAffy: Processing raw data from Affymetrix expression microarrays in Python.
Home-page: https://github.com/flo-compbio/pyaffy
Author: Florian Wagner
Author-email: florian.wagner@duke.edu
License: GPLv3
Keywords: affymetrix microarray rma expression normalization
Platform: UNKNOWN
Classifier: Development Status :: 3 - Alpha
Classifier: Intended Audience :: Developers
Classifier: Intended Audience :: Science/Research
Classifier: Topic :: Scientific/Engineering :: Bio-Informatics
Classifier: License :: OSI Approved :: GNU General Public License v3 (GPLv3)
Classifier: Programming Language :: Python :: 2.7
